fibers/__init__.py
fibers/_cfibers.cp37-win_amd64.pyd
fibers/_pyfibers.py
fibers_ddtest2-1.2.8.dist-info/LICENSE
fibers_ddtest2-1.2.8.dist-info/METADATA
fibers_ddtest2-1.2.8.dist-info/WHEEL
fibers_ddtest2-1.2.8.dist-info/top_level.txt
fibers_ddtest2-1.2.8.dist-info/RECORD
