Metadata-Version: 2.1
Name: fibers_ddtest2
Version: 1.2.8
Summary: Lightweight cooperative microthreads for Pyhton
Home-page: http://github.com/saghul/python-fibers
Author: Saúl Ibarra Corretgé
Author-email: saghul@gmail.com
Platform: POSIX
Platform: Microsoft Windows
Classifier: Development Status :: 5 - Production/Stable
Classifier: Intended Audience :: Developers
Classifier: License :: OSI Approved :: MIT License
Classifier: Operating System :: POSIX
Classifier: Operating System :: Microsoft :: Windows
Classifier: Programming Language :: Python
Classifier: Programming Language :: Python :: 3
Classifier: Programming Language :: Python :: 3.7
Classifier: Programming Language :: Python :: 3.8
Classifier: Programming Language :: Python :: 3.9
Classifier: Programming Language :: Python :: 3.10
Classifier: Programming Language :: Python :: Implementation :: CPython
Classifier: Programming Language :: Python :: Implementation :: PyPy
License-File: LICENSE
